pyghaseel/Ar_cleaner.py
pyghaseel/Cleaner.py
pyghaseel/En_cleaner.py
pyghaseel/Singleton.py
pyghaseel/__init__.py
pyghaseel-0.1.dist-info/METADATA
pyghaseel-0.1.dist-info/WHEEL
pyghaseel-0.1.dist-info/top_level.txt
pyghaseel-0.1.dist-info/RECORD
